intp.py
setup.cfg
setup.py
intp.egg-info/PKG-INFO
intp.egg-info/SOURCES.txt
intp.egg-info/dependency_links.txt
intp.egg-info/entry_points.txt
intp.egg-info/not-zip-safe
intp.egg-info/top_level.txt